dkdc_io/__init__.py
dkdc_io/config.py
dkdc_io/server.py
dkdc_io/cli/__init__.py
dkdc_io/cli/console.py
dkdc_io/tools/__init__.py
dkdc_io-0.0.1.dist-info/METADATA
dkdc_io-0.0.1.dist-info/WHEEL
dkdc_io-0.0.1.dist-info/entry_points.txt
dkdc_io-0.0.1.dist-info/RECORD
